polarini_focusini/__init__.py
polarini_focusini/_cli.py
polarini_focusini/debug_visualization.py
polarini_focusini/depth_estimation.py
polarini_focusini/infocus_detection.py
polarini_focusini-0.1.3.dist-info/METADATA
polarini_focusini-0.1.3.dist-info/WHEEL
polarini_focusini-0.1.3.dist-info/entry_points.txt
polarini_focusini-0.1.3.dist-info/top_level.txt
polarini_focusini-0.1.3.dist-info/RECORD
