Metadata-Version: 2.4
Name: polarini-focusini
Version: 0.1.3
Summary: Detect in-focus regions in images using depth estimation and Difference-of-Gaussian (DoG) extrema voting across depth bins.
Home-page: https://github.com/PolarNick239/PolariniFocusini
Author: Nikolai Poliarnyi
License: MIT
Classifier: Programming Language :: Python :: 3
Classifier: License :: OSI Approved :: MIT License
Classifier: Operating System :: OS Independent
Requires-Python: >=3.9
Requires-Dist: onnxruntime>=1.18.1
Requires-Dist: opencv-python>=4.8.0
Requires-Dist: numpy>=1.23.0
Requires-Dist: scipy>=1.10.0
Requires-Dist: matplotlib>=3.7.0
Requires-Dist: requests>=2.31.0
Requires-Dist: tqdm>=4.66.0
Requires-Dist: platformdirs>=4.2.0
Provides-Extra: cuda
Requires-Dist: onnxruntime-gpu>=1.18.1; extra == "cuda"
Provides-Extra: dev
Requires-Dist: pytest>=8.0.0; extra == "dev"
Requires-Dist: packaging>=24.0; extra == "dev"
Dynamic: author
Dynamic: classifier
Dynamic: description
Dynamic: description-content-type
Dynamic: home-page
Dynamic: license
Dynamic: provides-extra
Dynamic: requires-dist
Dynamic: requires-python
Dynamic: summary
